[
    {
        "user_message": "How do I utilize chromedb locally",
        "response": "To utilize Chromedb locally, you can follow the step-by-step guide provided in the fourth document of the Chromadb_cleaned.txt file. Here are the general steps:\n\n1. Install Chroma: You can install Chroma by following the instructions provided in the documentation. Chroma can be installed using pip, and it requires Python 3.6 or higher.\n\n2. Create a collection: A collection is a set of embeddings that can be used for building AI applications. You can create a collection by running the following command in the terminal:\n\n   ```\n   chroma create-collection <collection_name>\n   ```\n\n   Replace `<collection_name>` with the name you want to give to your collection.\n\n3. Add text documents to the collection: Once you have created a collection, you can add text documents to it. To add a text document, you can run the following command:\n\n   ```\n   chroma add-document <collection_name> <document_path>\n   ```\n\n   Replace `<collection_name>` with the name of your collection, and `<document_path>` with the path to the text document you want to add.\n\n4. Train the embeddings: After adding text documents to the collection, you need to train the embeddings. You can do this by running the following command:\n\n   ```\n   chroma train-embeddings <collection_name>\n   ```\n\n   This will train the embeddings for the text documents in your collection.\n\n5. Query the collection: Once you have trained the embeddings, you can query the collection to retrieve similar documents. You can do this by running the following command:\n\n   ```\n   chroma query <collection_name> <query_text>\n   ```\n\n   Replace `<collection_name>` with the name of your collection, and `<query_text>` with the text you want to use as a query.\n\nThese are the basic steps for using Chroma locally. You can also explore the other features and integrations provided by Chroma by referring to the third document in the Chromadb_cleaned.txt file.",
        "time": "2023-05-02 09:51:59.150111"
    },
    {
        "user_message": "Tell me about Elder Evils?",
        "response": "Elder Evils are powerful entities that exist beyond the boundaries of the known universe. They are not deities, but their power is immense, and their mere presence can threaten reality itself. These creatures are not interested in mortals except to wipe them out, and they are often campaign enders, as they are threats so powerful that they can bring an entire campaign setting to an end.\n\nUnlike other monsters in Dungeons & Dragons, Elder Evils are not just creatures with high Challenge Ratings. They are campaign capstones, and their abilities far outstrip those of even the most powerful player characters. In some cases, the PCs do not even confront the Elder Evil itself, but only a mighty extension of its foul will.\n\nThe secrecy of an Elder Evil depends on the needs of the Dungeon Master. If ending the world isn't on the horizon just yet, the foes described in the following chapters make exciting challenges for high-level adventurers. Each Elder Evil presented has one or more servants, and these servants are often just as dangerous as the Elder Evil itself.\n\nOne of the most famous Elder Evils is Atropus, a moon-like orb that is the stillborn afterbirth of the world's creation. Atropus is an undead entity that desires nothing less than the end of the entire multiverse. It is a terrifying foe that can only be defeated by the most powerful heroes.\n\nIntroducing an Elder Evil into a campaign can be a daunting task, but there are many signs that can bring the end times to the world. These signs can include strange weather patterns, the appearance of strange creatures, and even the sudden disappearance of entire cities. The Dungeon Master can use these signs to slowly build up the tension and create a sense of impending doom.\n\nIn addition to the Elder Evils themselves, the information also includes new feats and malevolent properties that add horror and power to Elder Evils and their servants. These can be used to make the foes even more terrifying and challenging for the players.\n\nOverall, Elder Evils are some of the most powerful and terrifying foes in Dungeons & Dragons. They are not to be taken lightly, and their presence can bring an entire campaign to an end. However, for those brave enough to face them, the rewards can be great, and the stories told will be legendary.",
        "time": "2023-05-04 12:26:02.063803"
    },
    {
        "user_message": "What's one of the scariest evils?",
        "response": "One of the scariest evils described in the supplement for the tabletop role-playing game is Atropus, an elder evil that desires the end of the entire multiverse. Atropus is an undead entity that resembles a massive, floating skull with tentacles and a gaping maw. It is said to have been created by an unknown force to destroy all life and bring about the end of existence itself.\n\nWhat makes Atropus particularly terrifying is its sheer power and the fact that it is not interested in mortals except to wipe them out. It is not a deity that can be bargained with or reasoned with, but an unstoppable force that exists solely to destroy. Atropus is also unique in that it is not bound to a specific plane of existence, but can move freely between them, making it nearly impossible to escape its wrath.\n\nThe supplement emphasizes that elder evils like Atropus are not just powerful monsters with impressive challenge ratings, but are campaign capstones that can change the world even if their genocidal plans are not completely realized. The mere presence of an elder evil can bring about the end times, and the characters must use all of their skills and resources to stop it.\n\nOverall, Atropus represents one of the scariest evils in the supplement, and its inclusion in a campaign is sure to provide a thrilling and terrifying experience for high-level adventurers.",
        "time": "2023-05-04 12:39:21.884453"
    },
    {
        "user_message": "Okay are there any heroes that could defeat an Elder Evil?",
        "response": "In the context of Dungeons & Dragons, defeating an Elder Evil is an incredibly difficult task, and it is unlikely that any single hero could do it alone. Elder evils are incredibly powerful beings that exist solely to destroy or remake creation, and their presence threatens reality itself. They are not deities and are not interested in mortals except to wipe them out. Elder evils are so powerful that even the gods think twice about standing against them.\n\nTo defeat an Elder Evil, a group of powerful heroes would need to band together and combine their skills and abilities to stand a chance. Even then, it would be a difficult and dangerous task, and the heroes would need to be prepared to make great sacrifices to succeed.\n\nThe heroes would need to gather powerful artifacts and weapons, seek out allies and information, and carefully plan their attack. They would need to be skilled in combat, magic, and diplomacy, as they may need to negotiate with other powerful beings to gain their aid.\n\nUltimately, the key to defeating an Elder Evil would be to find and exploit its weaknesses. These may be physical weaknesses, such as vulnerabilities to certain types of damage or attacks, or they may be psychological weaknesses, such as a fear of certain things or a desire for power or control.\n\nIn short, defeating an Elder Evil is an incredibly difficult task that would require a group of powerful heroes working together and making great sacrifices. It would be a grand and epic story arc that would test the limits of the characters and the players controlling them.",
        "time": "2023-05-04 13:12:07.602635"
    },
    {
        "page id": 5,
        "user_message": "What's the name of one elder evil?",
        "response": "One elder evil described in the supplement is known as Pandorym. Pandorym is a being of pure chaos and destruction, existing beyond the boundaries of reality. It seeks to unravel the fabric of existence and reduce everything to a state of formless chaos. Pandorym is said to be imprisoned in a realm of pure chaos, but its influence can still be felt in the mortal world. Its servants are chaotic and destructive creatures, and those who seek to release Pandorym are often driven mad by its whispers. Signs of Pandorym's influence include random and unpredictable natural disasters, sudden outbreaks of violence and chaos, and the appearance of strange and twisted creatures. Pandorym has maximum hit points per Hit Die, immunity to acid, and high damage reduction and spell resistance. It can summon chaotic creatures and has the ability to warp reality around it. Pandorym is considered one of the most dangerous and destructive elder evils, and its release would likely result in the end of the world.",
        "time": "2023-05-04 14:11:51.431570"
    },
    {
        "page id": 6,
        "user_message": "create the introduction to a scary story about Ettin",
        "response": "As the group of adventurers made their way through the dark and winding forest path, they couldn't shake the feeling that they were being watched. The hairs on the back of their necks stood on end, and they couldn't help but glance over their shoulders every few steps. They had heard rumors of ettins lurking in the area, two-headed giants that were known for their viciousness and unpredictability.\n\nAs they approached the site of their meeting with the cleric, they knew they were getting closer to the danger. About 30 minutes away, there was a cave off the path where six ettins were said to be lurking. The cave had an uninterrupted line of sight to the path, putting the encounter distance at 40 feet. But the conditions of the night allowed the ettins a chance to hear the PCs before they came within line of sight.\n\nThe adventurers knew they had to be careful. The ettins were being used as guards by the cleric, who had persuaded or bullied them to aid him in his cause. The creatures had no language of their own, but spoke a pidgin of Orc, Goblin, and Giant. Those who could speak any of these languages had to succeed on a DC 15 Intelligence check to communicate with an ettin.\n\nThe group couldn't help but feel a sense of dread as they approached the cave. The bones of many orcs littered the floor, the remains of curious creatures who had sought to follow the cleric back to his starting point. The ettins were fanatical in their loyalty to the cleric, and guarded the pass with their lives.\n\nThe adventurers knew they had to be cautious, but they couldn't shake the feeling that they were walking into a trap. The ettins had a tactic of not moving until they heard the PCs, and they were quite emphatic about it. The group knew that they had to be prepared for anything, and that they were about to face one of the most terrifying creatures in the forest - the ettin.",
        "time": "2023-05-04 16:15:22.233178"
    },
    {
        "page id": 7,
        "user_message": "Tell me about the Unapproachable East",
        "response": "The Unapproachable East is a region in the world of Faern that is known for its ancient mysteries, powerful magic, and endless strife. It is a crossroads where East meets West and is a battleground where human races and realms clash. The region is home to tribes that value freedom more than their lives and slaves who groan under the worst kind of sorcerous oppression. The Unapproachable East is also known for its exotic beauty and hell-spawned peril.\n\nThe region is divided into five different lands, each with its own perils and mysteries. Thay is notorious for its magical experimentation and cruel necromancy, while the Witches of Rashemen guard secrets of magical lore and are vigilant against the next manifestation of Thay's ambitions. The Great Dale is governed by a council of druids, and the independent clanholds of the Great Dale stand amid the ancient ruins of old Narfell, a demon-haunted realm whose dark legacy still threatens nearby lands a thousand years after its destruction.\n\nThe Unapproachable East is a land of proud barbarians, forest-grown ruins, and dreadful wizardry. It is a world filled with ancient empires, terrible magic, and the clash of human races and realms. Unlike the lands of the west, where elven and dwarven realms of great antiquity shielded the young human kingdoms from monstrous threats, few nonhuman realms have left their mark upon the east. Instead, spellcasters rule entire nations with unshakable strength and determination.\n\nThe Unapproachable East is a place of secrets and threats, and characters from other parts of Faern find it inscrutable, unknown, and alluring. The region is a plot for mercantile and military domination of all the Unapproachable East and after that, the world.\n\nThe Unapproachable East is a fascinating and dangerous region that offers endless opportunities for adventure and exploration. Its ancient ruins, powerful magic, and diverse cultures make it a rich and",
        "time": "2023-05-09 21:56:21.561437"
    },
    {
        "page id": 8,
        "user_message": "Who's the most powerful wizard in the Unapproachable East?",
        "response": "It is difficult to determine who the most powerful wizard in the Unapproachable East is, as the region is home to many powerful spellcasters with different specialties and allegiances. However, some notable wizards and magical organizations in the region include:\n\n- The Red Wizards of Thay: This organization is known for its mastery of magic and ruthless pursuit of power. The Red Wizards are led by a council of zulkirs, each of whom specializes in a different school of magic. The most powerful zulkir is Szass Tam, who is also a lich and the ruler of Thay. The Red Wizards are feared and respected throughout the region for their magical might and political influence.\n\n- The Witches of Rashemen: These spellcasters are known for their unique blend of shamanism and arcane magic. The Witches are led by the Iron Lord, a powerful warrior who wears a magical mask that grants her immense strength and endurance. The Witches guard their secrets closely and are suspicious of outsiders, but they are also known for their wisdom and compassion.\n\n- The Arcane Brotherhood: This organization is based in the city of Llorkh and is dedicated to the study and practice of magic. The Brotherhood is led by the archmage Arcturia, who is said to be one of the most powerful wizards in the region. The Brotherhood is known for its research into forbidden magic and its willingness to experiment with dangerous spells.\n\n- The Simbul: This powerful sorceress is said to be the chosen of Mystra, the goddess of magic. The Simbul is known for her wild and unpredictable nature, as well as her immense magical power. She is a force to be reckoned with and is feared by many in the region.\n\n- The Harpers: This organization is dedicated to preserving the balance of power in the world and protecting the innocent from harm. The Harpers have many members in the Unapproachable East, including powerful wizards such as Khelben \"Black",
        "time": "2023-05-09 23:04:05.999295"
    },
    {
        "page id": 9,
        "user_message": "okay, tell me more about Szass Tam",
        "response": "Szass Tam is one of the eight zulkirs who govern the country of Thay. He is considered to be the most powerful and influential of the zulkirs and is known for his mastery of necromancy. Szass Tam is a lich, which means that he has achieved immortality by transferring his soul into a phylactery. He is also the ruler of the Tharch of Thaymount, which is one of the most important tharchs in the country.\n\nSzass Tam is a ruthless and cunning leader who is willing to do whatever it takes to achieve his goals. He is known for his use of undead soldiers, which he creates through his mastery of necromancy. These undead soldiers are a key part of Thay's military, and they are feared by many of Thay's enemies.\n\nDespite his power and influence, Szass Tam is not universally loved by the other zulkirs. Some of them believe that his use of undead soldiers is a dangerous and unpredictable tactic that could backfire on Thay. Others are concerned that his ambition could lead to him trying to seize power from the other zulkirs.\n\nOverall, Szass Tam is a complex and fascinating character who plays a key role in the politics and power struggles of Thay. His mastery of necromancy and his ruthless ambition make him a formidable opponent, and his actions will have a significant impact on the future of Thay and the surrounding regions.",
        "time": "2023-05-09 23:11:01.843134"
    },
    {
        "page id": 10,
        "user_message": "tell me how Szass Tam will advance the campaign",
        "response": "Szass Tam, as the most powerful zulkir in Thay, will likely play a key role in advancing the campaign of the Red Wizards. His entrenched position in Thay's government means that he has significant influence over the country's policies and actions. As the Red Wizards continue their plan to infiltrate other nations through economic means, Szass Tam's expertise in magic and manipulation will be invaluable in achieving this goal.\n\nOne potential area where Szass Tam could advance the campaign is in his dealings with Aglarond. Thay has long sought to penetrate Aglarond, but has been unable to do so due to the country's natural defenses. Szass Tam may use his magical abilities to find a way to bypass these defenses, or he may work to undermine Aglarond from within by infiltrating its economy and political structures.\n\nAnother potential area where Szass Tam could advance the campaign is in his dealings with the Simbul. The Red Wizards have a particular hatred for the Simbul, who has thwarted their efforts in the past. Szass Tam may use his influence to try and eliminate the Simbul, or he may work to weaken her power and influence in order to make it easier for the Red Wizards to achieve their goals.\n\nFinally, Szass Tam's control over Thay's slave trade could also play a role in advancing the campaign. Thay's use of skilled slaves has been a key part of its economy and military power, and Szass Tam may use this resource to further the Red Wizards' goals. For example, he may use his control over the slave trade to infiltrate other nations by sending skilled slaves as spies or agents.\n\nOverall, Szass Tam's position as the most powerful zulkir in Thay and his expertise in magic and manipulation make him a key player in advancing the Red Wizards' campaign. His actions will likely have a significant impact on the success or failure of the Red Wizards' plans.",
        "time": "2023-05-10 00:44:46.268366"
    },
    {
        "page id": 11,
        "user_message": "tell me how Szass Tam will advance the campaign",
        "response": "Szass Tam, as the zulkir of necromancy and the leader of the Red Wizards of Thay, is likely to advance the campaign in several ways. \n\nFirstly, he is a powerful necromancer and can raise and control undead armies. This makes him a formidable opponent in battle and a potential threat to neighboring countries like Aglarond. He may use his powers to try and breach the Watchwall or to launch surprise attacks on Aglarond's borders. \n\nSecondly, Szass Tam is known for his cunning and manipulative nature. He may use Thay's mercantile power to infiltrate other countries and gather information on their weaknesses. Once he has enough information, he may use it to undermine their economies or launch covert attacks. He may also use his powers of persuasion to turn influential people in other countries to his side, using them as pawns in his larger scheme. \n\nThirdly, Szass Tam may use the Umber Council and their plant monsters to his advantage. He may direct them to attack Aglarond's borders or use them to distract the Simbul while he launches a surprise attack. He may also use the plant monsters to create chaos in other countries, making it easier for Thay to infiltrate and take over. \n\nOverall, Szass Tam's powers and cunning make him a formidable opponent in any campaign. His ability to raise undead armies, manipulate other countries, and use the Umber Council to his advantage make him a dangerous foe to face. It will take careful planning and strategic thinking to defeat him and stop Thay's expansionist plans.",
        "time": "2023-05-10 01:03:18.685775"
    },
    {
        "page id": 12,
        "user_message": "How will Szass Tam advance the campaign",
        "response": "Szass Tam, as one of the eight zulkirs who run the government of Thay, has a clear goal of world domination. The current plan of the Red Wizards is to use the greed of other people as a tool against them by offering discounted goods to work their way into every major economy on Faern. Once the Red Wizards have become entrenched in a nation, they can learn enough about the locals to dismantle them quietly from within.\n\nTo advance the campaign, Szass Tam and the other zulkirs will likely continue to use their economic power to infiltrate and manipulate other nations. They will likely focus on expanding their influence in the eleven tharchs, appointing loyal tharchions and autharchs to oversee various locations and projects for them.\n\nTyraturos, with its thriving slave trade, may be a particularly important tharch for Szass Tam to focus on. By controlling the slave trade, the Red Wizards can not only make a profit but also have a source of labor for their own projects.\n\nThe city of Amruthar may also be a target for Szass Tam and the Red Wizards. The Dependents, who want to maintain the status quo and continue to be under Thay's rule, may be useful allies for the Red Wizards. However, the Independents, who want to sever all ties with Thay, could be a threat. Szass Tam may try to manipulate the factions to his advantage, perhaps by offering the Independents a deal that benefits both parties.\n\nThe Umber Council, with their plant monsters, could also be a valuable asset for Szass Tam. He may try to strengthen his alliance with the undead druids and use their monsters to attack the people of Aglarond.\n\nOverall, Szass Tam's strategy will likely involve using economic power, political manipulation, and alliances with powerful allies like the Umber Council to expand Thay's influence and eventually achieve world domination.",
        "time": "2023-05-10 01:50:20.754961"
    }
]